wagtail_exportcsv/__init__.py
wagtail_exportcsv/admin.py
wagtail_exportcsv/apps.py
wagtail_exportcsv/tests.py
wagtail_exportcsv/templates/wagtail_exportcsv/exportcsv.html
wagtail_exportcsv-0.1.dist-info/METADATA
wagtail_exportcsv-0.1.dist-info/RECORD
wagtail_exportcsv-0.1.dist-info/WHEEL
wagtail_exportcsv-0.1.dist-info/top_level.txt
