Metadata-Version: 2.1
Name: wagtail-exportcsv
Version: 0.1
Summary: A simple Django wagtail app to download form submissions as CSV.
Home-page: https://github.com/7aleb/wagtail-exportcsv
Author: Mohammad Taleb
Author-email: shimultaleb@gamil.com
License: BSD License
Platform: UNKNOWN
Classifier: Environment :: Web Environment
Classifier: Framework :: Django
Classifier: Framework :: Django :: 2.1
Classifier: Framework :: Wagtail
Classifier: Intended Audience :: Developers
Classifier: License :: OSI Approved :: BSD License
Classifier: Operating System :: OS Independent
Classifier: Programming Language :: Python
Classifier: Programming Language :: Python :: 3.5
Classifier: Programming Language :: Python :: 3.6
Classifier: Topic :: Internet :: WWW/HTTP
Classifier: Topic :: Internet :: WWW/HTTP :: Dynamic Content
Requires-Dist: django-import-export
